bravado_falcon/__init__.py
bravado_falcon-0.0.1.dist-info/DESCRIPTION.rst
bravado_falcon-0.0.1.dist-info/METADATA
bravado_falcon-0.0.1.dist-info/RECORD
bravado_falcon-0.0.1.dist-info/WHEEL
bravado_falcon-0.0.1.dist-info/metadata.json
bravado_falcon-0.0.1.dist-info/top_level.txt
