Metadata-Version: 1.1
Name: bravado-falcon
Version: 0.0.1
Summary: Integration of Falcon API unit tests with Bravado.
Home-page: https://github.com/butla/bravado-falcon
Author: Michał Bultrowicz
Author-email: michal.bultrowicz@gmail.com
License: MIT
Keywords: falcon bravado test
Platform: UNKNOWN
Classifier: Development Status :: 4 - Beta
Classifier: Intended Audience :: Developers
Classifier: License :: OSI Approved :: MIT License
Classifier: Natural Language :: English
Classifier: Programming Language :: Python :: 2.7
Classifier: Programming Language :: Python :: 3.4
Classifier: Operating System :: MacOS :: MacOS X
Classifier: Operating System :: Microsoft :: Windows
Classifier: Operating System :: POSIX
